{"meta":{"dataYear":2024,"page":127,"pageSize":20,"total":4908,"totalPages":246,"exportedAt":"2026-05-29T20:08:43.607Z"},"lenders":[{"lei":"549300URHBBJ2KIQ3616","name":"Foresight Bank","nmls":"","type":"Bank","dataYear":2024,"orig":132,"dollarVol":39880000,"branches":1,"states":2,"fico":620,"ltv":97,"dti":50,"rate":6.257,"hmdaRate":null,"rateSource":"estimated","products":["Conventional"],"conf":70,"hmdaInsights":{"schemaVersion":2,"reportingYear":2024,"totalApplications":153,"totalOriginated":132,"actionTaken":{"1":132,"2":12,"3":6,"4":3,"5":0,"6":0,"7":0,"8":0},"denialReasons":{"1":0,"2":0,"3":0,"4":0,"5":0,"6":0,"7":0,"8":0,"9":0,"10":0},"denialReasonsSuppressedCount":6,"denialCount":6,"withdrawalCount":3,"incompleteCount":0,"approvedNotAcceptedCount":12,"purchasedLoanCount":0,"originatedMedianInterestRate":null,"originatedMedianRateSpread":null,"originatedMedianLoanTermMonths":null,"originatedMedianCltv":null,"originatedMedianDti":null,"spreadSampleSize":0,"termSampleSize":0,"cltvSampleSize":0,"dtiSampleSize":0,"interestRateSampleSize":0,"loanTypeSummary":{"1":{"applications":153,"originated":132,"dollarVolume":39880000},"2":{"applications":0,"originated":0,"dollarVolume":0},"3":{"applications":0,"originated":0,"dollarVolume":0},"4":{"applications":0,"originated":0,"dollarVolume":0}},"lienOnOriginated":{"1":120,"2":12},"hoepaOnOriginated":{"2":75,"3":57},"submissionOnApplications":{"1111":153},"initiallyPayableOnApplications":{"1111":153},"geographyHhiStates":null,"topStateOriginationShare":null,"stateBreakdown":[],"topCounties":[],"topMsas":[],"quarterlyFromLar":null,"monthlyFromLar":null,"hasActionTakenDate":false,"databrowserSource":false,"source":"modifiedLar-2024-direct","note":"Aggregated directly from FFIEC modified-LAR per-institution file."},"nmlsNumber":null,"legalName":"Foresight Bank","dba":null,"originationBreakdown":{"byProduct":{"Conventional":{"originated":132,"approximate":false,"hmdaLoanType":1},"FHA":{"originated":0,"approximate":false,"hmdaLoanType":2},"VA":{"originated":0,"approximate":false,"hmdaLoanType":3},"USDA":{"originated":0,"approximate":false,"hmdaLoanType":4}},"totalOriginatedUnits":132,"mergedInsightsFromYear":2024},"declinations":{"available":true,"mergedFromReportingYear":2024,"totalApplications":153,"deniedApplications":6,"withdrawnApplications":3,"incompleteApplications":0,"approvedNotAccepted":12,"purchasedLoans":0,"denialReasons":{"1":0,"2":0,"3":0,"4":0,"5":0,"6":0,"7":0,"8":0,"9":0,"10":0},"denialReasonsSuppressedCount":6},"rank":2541},{"lei":"549300UXCRU4C6HBN492","name":"FCS Financial, FLCA","nmls":"","type":"IMB","dataYear":2024,"orig":132,"dollarVol":30090000,"branches":1,"states":2,"fico":620,"ltv":97,"dti":50,"rate":7.4,"hmdaRate":7.4,"rateSource":"hmda-mlar","products":["Conventional"],"conf":70,"hmdaInsights":{"schemaVersion":2,"reportingYear":2024,"totalApplications":171,"totalOriginated":132,"actionTaken":{"1":132,"2":0,"3":14,"4":21,"5":4,"6":0,"7":0,"8":0},"denialReasons":{"1":9,"2":0,"3":2,"4":1,"5":0,"6":0,"7":0,"8":0,"9":2,"10":0},"denialReasonsSuppressedCount":0,"denialCount":14,"withdrawalCount":21,"incompleteCount":4,"approvedNotAcceptedCount":0,"purchasedLoanCount":0,"originatedMedianInterestRate":7.4,"originatedMedianRateSpread":0.78,"originatedMedianLoanTermMonths":301,"originatedMedianCltv":51.725,"originatedMedianDti":40,"spreadSampleSize":131,"termSampleSize":132,"cltvSampleSize":132,"dtiSampleSize":38,"interestRateSampleSize":132,"loanTypeSummary":{"1":{"applications":171,"originated":132,"dollarVolume":30090000},"2":{"applications":0,"originated":0,"dollarVolume":0},"3":{"applications":0,"originated":0,"dollarVolume":0},"4":{"applications":0,"originated":0,"dollarVolume":0}},"lienOnOriginated":{"1":128,"2":4},"hoepaOnOriginated":{"2":131,"3":1},"submissionOnApplications":{"1":171},"initiallyPayableOnApplications":{"1":171},"geographyHhiStates":null,"topStateOriginationShare":null,"stateBreakdown":[],"topCounties":[],"topMsas":[],"quarterlyFromLar":null,"monthlyFromLar":null,"hasActionTakenDate":false,"databrowserSource":false,"source":"modifiedLar-2024-direct","note":"Aggregated directly from FFIEC modified-LAR per-institution file."},"nmlsNumber":null,"legalName":"FCS Financial, FLCA","dba":null,"originationBreakdown":{"byProduct":{"Conventional":{"originated":132,"approximate":false,"hmdaLoanType":1},"FHA":{"originated":0,"approximate":false,"hmdaLoanType":2},"VA":{"originated":0,"approximate":false,"hmdaLoanType":3},"USDA":{"originated":0,"approximate":false,"hmdaLoanType":4}},"totalOriginatedUnits":132,"mergedInsightsFromYear":2024},"declinations":{"available":true,"mergedFromReportingYear":2024,"totalApplications":171,"deniedApplications":14,"withdrawnApplications":21,"incompleteApplications":4,"approvedNotAccepted":0,"purchasedLoans":0,"denialReasons":{"1":9,"2":0,"3":2,"4":1,"5":0,"6":0,"7":0,"8":0,"9":2,"10":0},"denialReasonsSuppressedCount":0},"rank":2542},{"lei":"549300Y37WHI3S8KVE74","name":"MERCED SCHOOL EMPLOYEES FEDERAL CREDIT UNION","nmls":"","type":"Credit Union","dataYear":2024,"orig":132,"dollarVol":14990000,"branches":1,"states":1,"fico":620,"ltv":97,"dti":50,"rate":6.267,"hmdaRate":null,"rateSource":"estimated","products":["Conventional"],"conf":70,"hmdaInsights":{"schemaVersion":2,"reportingYear":2024,"totalApplications":177,"totalOriginated":132,"actionTaken":{"1":132,"2":4,"3":17,"4":2,"5":3,"6":0,"7":2,"8":17},"denialReasons":{"1":12,"2":1,"3":3,"4":2,"5":0,"6":1,"7":0,"8":0,"9":1,"10":0},"denialReasonsSuppressedCount":0,"denialCount":17,"withdrawalCount":2,"incompleteCount":3,"approvedNotAcceptedCount":4,"purchasedLoanCount":0,"originatedMedianInterestRate":null,"originatedMedianRateSpread":null,"originatedMedianLoanTermMonths":null,"originatedMedianCltv":57.064,"originatedMedianDti":40,"spreadSampleSize":0,"termSampleSize":0,"cltvSampleSize":132,"dtiSampleSize":51,"interestRateSampleSize":0,"loanTypeSummary":{"1":{"applications":177,"originated":132,"dollarVolume":14990000},"2":{"applications":0,"originated":0,"dollarVolume":0},"3":{"applications":0,"originated":0,"dollarVolume":0},"4":{"applications":0,"originated":0,"dollarVolume":0}},"lienOnOriginated":{"1":61,"2":71},"hoepaOnOriginated":{"2":132},"submissionOnApplications":{"1111":177},"initiallyPayableOnApplications":{"1111":177},"geographyHhiStates":null,"topStateOriginationShare":null,"stateBreakdown":[],"topCounties":[],"topMsas":[],"quarterlyFromLar":null,"monthlyFromLar":null,"hasActionTakenDate":false,"databrowserSource":false,"source":"modifiedLar-2024-direct","note":"Aggregated directly from FFIEC modified-LAR per-institution file."},"nmlsNumber":null,"legalName":"MERCED SCHOOL EMPLOYEES FEDERAL CREDIT UNION","dba":null,"originationBreakdown":{"byProduct":{"Conventional":{"originated":132,"approximate":false,"hmdaLoanType":1},"FHA":{"originated":0,"approximate":false,"hmdaLoanType":2},"VA":{"originated":0,"approximate":false,"hmdaLoanType":3},"USDA":{"originated":0,"approximate":false,"hmdaLoanType":4}},"totalOriginatedUnits":132,"mergedInsightsFromYear":2024},"declinations":{"available":true,"mergedFromReportingYear":2024,"totalApplications":177,"deniedApplications":17,"withdrawnApplications":2,"incompleteApplications":3,"approvedNotAccepted":4,"purchasedLoans":0,"denialReasons":{"1":12,"2":1,"3":3,"4":2,"5":0,"6":1,"7":0,"8":0,"9":1,"10":0},"denialReasonsSuppressedCount":0},"rank":2543},{"lei":"549300YPUST7CSVL4680","name":"FNB Community Bank","nmls":"","type":"Bank","dataYear":2024,"orig":132,"dollarVol":17850000,"branches":1,"states":1,"fico":620,"ltv":97,"dti":50,"rate":6.204,"hmdaRate":null,"rateSource":"estimated","products":["Conventional"],"conf":70,"hmdaInsights":{"schemaVersion":2,"reportingYear":2024,"totalApplications":203,"totalOriginated":132,"actionTaken":{"1":132,"2":14,"3":44,"4":13,"5":0,"6":0,"7":0,"8":0},"denialReasons":{"1":0,"2":0,"3":0,"4":0,"5":0,"6":0,"7":0,"8":0,"9":0,"10":0},"denialReasonsSuppressedCount":44,"denialCount":44,"withdrawalCount":13,"incompleteCount":0,"approvedNotAcceptedCount":14,"purchasedLoanCount":0,"originatedMedianInterestRate":null,"originatedMedianRateSpread":null,"originatedMedianLoanTermMonths":null,"originatedMedianCltv":null,"originatedMedianDti":null,"spreadSampleSize":0,"termSampleSize":0,"cltvSampleSize":0,"dtiSampleSize":0,"interestRateSampleSize":0,"loanTypeSummary":{"1":{"applications":203,"originated":132,"dollarVolume":17850000},"2":{"applications":0,"originated":0,"dollarVolume":0},"3":{"applications":0,"originated":0,"dollarVolume":0},"4":{"applications":0,"originated":0,"dollarVolume":0}},"lienOnOriginated":{"1":98,"2":34},"hoepaOnOriginated":{"2":68,"3":64},"submissionOnApplications":{"1111":203},"initiallyPayableOnApplications":{"1111":203},"geographyHhiStates":null,"topStateOriginationShare":null,"stateBreakdown":[],"topCounties":[],"topMsas":[],"quarterlyFromLar":null,"monthlyFromLar":null,"hasActionTakenDate":false,"databrowserSource":false,"source":"modifiedLar-2024-direct","note":"Aggregated directly from FFIEC modified-LAR per-institution file."},"nmlsNumber":null,"legalName":"FNB Community Bank","dba":null,"originationBreakdown":{"byProduct":{"Conventional":{"originated":132,"approximate":false,"hmdaLoanType":1},"FHA":{"originated":0,"approximate":false,"hmdaLoanType":2},"VA":{"originated":0,"approximate":false,"hmdaLoanType":3},"USDA":{"originated":0,"approximate":false,"hmdaLoanType":4}},"totalOriginatedUnits":132,"mergedInsightsFromYear":2024},"declinations":{"available":true,"mergedFromReportingYear":2024,"totalApplications":203,"deniedApplications":44,"withdrawnApplications":13,"incompleteApplications":0,"approvedNotAccepted":14,"purchasedLoans":0,"denialReasons":{"1":0,"2":0,"3":0,"4":0,"5":0,"6":0,"7":0,"8":0,"9":0,"10":0},"denialReasonsSuppressedCount":44},"rank":2544},{"lei":"549300ZD18AVSD0OG331","name":"GLENDENNING MORTGAGE CORPORATION","nmls":"","type":"IMB","dataYear":2024,"orig":132,"dollarVol":47750000,"branches":1,"states":3,"fico":620,"ltv":97,"dti":50,"rate":6.99,"hmdaRate":6.99,"rateSource":"hmda-mlar","products":["Conventional","FHA","VA"],"conf":70,"hmdaInsights":{"schemaVersion":2,"reportingYear":2024,"totalApplications":152,"totalOriginated":132,"actionTaken":{"1":132,"2":0,"3":9,"4":11,"5":0,"6":0,"7":0,"8":0},"denialReasons":{"1":1,"2":0,"3":1,"4":5,"5":1,"6":0,"7":0,"8":0,"9":1,"10":0},"denialReasonsSuppressedCount":0,"denialCount":9,"withdrawalCount":11,"incompleteCount":0,"approvedNotAcceptedCount":0,"purchasedLoanCount":0,"originatedMedianInterestRate":6.99,"originatedMedianRateSpread":0.454,"originatedMedianLoanTermMonths":360,"originatedMedianCltv":75,"originatedMedianDti":42,"spreadSampleSize":129,"termSampleSize":129,"cltvSampleSize":132,"dtiSampleSize":82,"interestRateSampleSize":132,"loanTypeSummary":{"1":{"applications":135,"originated":118,"dollarVolume":41740000},"2":{"applications":12,"originated":10,"dollarVolume":3740000},"3":{"applications":5,"originated":4,"dollarVolume":2270000},"4":{"applications":0,"originated":0,"dollarVolume":0}},"lienOnOriginated":{"1":117,"2":15},"hoepaOnOriginated":{"2":119,"3":13},"submissionOnApplications":{"1":152},"initiallyPayableOnApplications":{"1":152},"geographyHhiStates":null,"topStateOriginationShare":null,"stateBreakdown":[],"topCounties":[],"topMsas":[],"quarterlyFromLar":null,"monthlyFromLar":null,"hasActionTakenDate":false,"databrowserSource":false,"source":"modifiedLar-2024-direct","note":"Aggregated directly from FFIEC modified-LAR per-institution file."},"nmlsNumber":null,"legalName":"GLENDENNING MORTGAGE CORPORATION","dba":null,"originationBreakdown":{"byProduct":{"Conventional":{"originated":118,"approximate":false,"hmdaLoanType":1},"FHA":{"originated":10,"approximate":false,"hmdaLoanType":2},"VA":{"originated":4,"approximate":false,"hmdaLoanType":3},"USDA":{"originated":0,"approximate":false,"hmdaLoanType":4}},"totalOriginatedUnits":132,"mergedInsightsFromYear":2024},"declinations":{"available":true,"mergedFromReportingYear":2024,"totalApplications":152,"deniedApplications":9,"withdrawnApplications":11,"incompleteApplications":0,"approvedNotAccepted":0,"purchasedLoans":0,"denialReasons":{"1":1,"2":0,"3":1,"4":5,"5":1,"6":0,"7":0,"8":0,"9":1,"10":0},"denialReasonsSuppressedCount":0},"rank":2545},{"lei":"549300E5GFWPFRJR4I76","name":"First Northern Bank and Trust Company","nmls":"","type":"Bank","dataYear":2024,"orig":132,"dollarVol":28710000,"branches":1,"states":2,"fico":620,"ltv":97,"dti":50,"rate":6.387,"hmdaRate":null,"rateSource":"estimated","products":["Conventional"],"conf":70,"hmdaInsights":{"schemaVersion":2,"reportingYear":2024,"totalApplications":191,"totalOriginated":132,"actionTaken":{"1":132,"2":6,"3":28,"4":23,"5":2,"6":0,"7":0,"8":0},"denialReasons":{"1":0,"2":0,"3":0,"4":0,"5":0,"6":0,"7":0,"8":0,"9":0,"10":0},"denialReasonsSuppressedCount":28,"denialCount":28,"withdrawalCount":23,"incompleteCount":2,"approvedNotAcceptedCount":6,"purchasedLoanCount":0,"originatedMedianInterestRate":null,"originatedMedianRateSpread":null,"originatedMedianLoanTermMonths":null,"originatedMedianCltv":null,"originatedMedianDti":null,"spreadSampleSize":0,"termSampleSize":0,"cltvSampleSize":0,"dtiSampleSize":0,"interestRateSampleSize":0,"loanTypeSummary":{"1":{"applications":191,"originated":132,"dollarVolume":28710000},"2":{"applications":0,"originated":0,"dollarVolume":0},"3":{"applications":0,"originated":0,"dollarVolume":0},"4":{"applications":0,"originated":0,"dollarVolume":0}},"lienOnOriginated":{"1":112,"2":20},"hoepaOnOriginated":{"2":97,"3":35},"submissionOnApplications":{"1111":191},"initiallyPayableOnApplications":{"1111":191},"geographyHhiStates":null,"topStateOriginationShare":null,"stateBreakdown":[],"topCounties":[],"topMsas":[],"quarterlyFromLar":null,"monthlyFromLar":null,"hasActionTakenDate":false,"databrowserSource":false,"source":"modifiedLar-2024-direct","note":"Aggregated directly from FFIEC modified-LAR per-institution file."},"nmlsNumber":null,"legalName":"First Northern Bank and Trust Company","dba":null,"originationBreakdown":{"byProduct":{"Conventional":{"originated":132,"approximate":false,"hmdaLoanType":1},"FHA":{"originated":0,"approximate":false,"hmdaLoanType":2},"VA":{"originated":0,"approximate":false,"hmdaLoanType":3},"USDA":{"originated":0,"approximate":false,"hmdaLoanType":4}},"totalOriginatedUnits":132,"mergedInsightsFromYear":2024},"declinations":{"available":true,"mergedFromReportingYear":2024,"totalApplications":191,"deniedApplications":28,"withdrawnApplications":23,"incompleteApplications":2,"approvedNotAccepted":6,"purchasedLoans":0,"denialReasons":{"1":0,"2":0,"3":0,"4":0,"5":0,"6":0,"7":0,"8":0,"9":0,"10":0},"denialReasonsSuppressedCount":28},"rank":2546},{"lei":"2549001EL4XFDHGNJO24","name":"USC Credit Union","nmls":"","type":"Credit Union","dataYear":2024,"orig":131,"dollarVol":38535000,"branches":1,"states":1,"fico":620,"ltv":97,"dti":50,"rate":7.125,"hmdaRate":7.125,"rateSource":"hmda-mlar","products":["Conventional"],"conf":70,"hmdaInsights":{"schemaVersion":2,"reportingYear":2024,"totalApplications":223,"totalOriginated":131,"actionTaken":{"1":131,"2":9,"3":43,"4":38,"5":2,"6":0,"7":0,"8":0},"denialReasons":{"1":23,"2":1,"3":19,"4":11,"5":0,"6":0,"7":0,"8":0,"9":0,"10":0},"denialReasonsSuppressedCount":0,"denialCount":43,"withdrawalCount":38,"incompleteCount":2,"approvedNotAcceptedCount":9,"purchasedLoanCount":0,"originatedMedianInterestRate":7.125,"originatedMedianRateSpread":1.079,"originatedMedianLoanTermMonths":180,"originatedMedianCltv":63.36,"originatedMedianDti":43,"spreadSampleSize":130,"termSampleSize":131,"cltvSampleSize":131,"dtiSampleSize":85,"interestRateSampleSize":131,"loanTypeSummary":{"1":{"applications":223,"originated":131,"dollarVolume":38535000},"2":{"applications":0,"originated":0,"dollarVolume":0},"3":{"applications":0,"originated":0,"dollarVolume":0},"4":{"applications":0,"originated":0,"dollarVolume":0}},"lienOnOriginated":{"1":49,"2":82},"hoepaOnOriginated":{"2":129,"3":2},"submissionOnApplications":{"1":223},"initiallyPayableOnApplications":{"1":217,"3":6},"geographyHhiStates":null,"topStateOriginationShare":null,"stateBreakdown":[],"topCounties":[],"topMsas":[],"quarterlyFromLar":null,"monthlyFromLar":null,"hasActionTakenDate":false,"databrowserSource":false,"source":"modifiedLar-2024-direct","note":"Aggregated directly from FFIEC modified-LAR per-institution file."},"nmlsNumber":null,"legalName":"USC Credit Union","dba":null,"originationBreakdown":{"byProduct":{"Conventional":{"originated":131,"approximate":false,"hmdaLoanType":1},"FHA":{"originated":0,"approximate":false,"hmdaLoanType":2},"VA":{"originated":0,"approximate":false,"hmdaLoanType":3},"USDA":{"originated":0,"approximate":false,"hmdaLoanType":4}},"totalOriginatedUnits":131,"mergedInsightsFromYear":2024},"declinations":{"available":true,"mergedFromReportingYear":2024,"totalApplications":223,"deniedApplications":43,"withdrawnApplications":38,"incompleteApplications":2,"approvedNotAccepted":9,"purchasedLoans":0,"denialReasons":{"1":23,"2":1,"3":19,"4":11,"5":0,"6":0,"7":0,"8":0,"9":0,"10":0},"denialReasonsSuppressedCount":0},"rank":2547},{"lei":"2549009GERLEDM651T51","name":"Vermillion State Bank","nmls":"","type":"Bank","dataYear":2024,"orig":131,"dollarVol":30895000,"branches":1,"states":5,"fico":620,"ltv":97,"dti":50,"rate":6.432,"hmdaRate":null,"rateSource":"estimated","products":["Conventional"],"conf":70,"hmdaInsights":{"schemaVersion":2,"reportingYear":2024,"totalApplications":136,"totalOriginated":131,"actionTaken":{"1":131,"2":0,"3":1,"4":4,"5":0,"6":0,"7":0,"8":0},"denialReasons":{"1":0,"2":0,"3":0,"4":0,"5":0,"6":0,"7":0,"8":0,"9":0,"10":0},"denialReasonsSuppressedCount":1,"denialCount":1,"withdrawalCount":4,"incompleteCount":0,"approvedNotAcceptedCount":0,"purchasedLoanCount":0,"originatedMedianInterestRate":null,"originatedMedianRateSpread":null,"originatedMedianLoanTermMonths":null,"originatedMedianCltv":null,"originatedMedianDti":null,"spreadSampleSize":0,"termSampleSize":0,"cltvSampleSize":0,"dtiSampleSize":0,"interestRateSampleSize":0,"loanTypeSummary":{"1":{"applications":136,"originated":131,"dollarVolume":30895000},"2":{"applications":0,"originated":0,"dollarVolume":0},"3":{"applications":0,"originated":0,"dollarVolume":0},"4":{"applications":0,"originated":0,"dollarVolume":0}},"lienOnOriginated":{"1":91,"2":40},"hoepaOnOriginated":{"2":127,"3":4},"submissionOnApplications":{"1111":136},"initiallyPayableOnApplications":{"1111":136},"geographyHhiStates":null,"topStateOriginationShare":null,"stateBreakdown":[],"topCounties":[],"topMsas":[],"quarterlyFromLar":null,"monthlyFromLar":null,"hasActionTakenDate":false,"databrowserSource":false,"source":"modifiedLar-2024-direct","note":"Aggregated directly from FFIEC modified-LAR per-institution file."},"nmlsNumber":null,"legalName":"Vermillion State Bank","dba":null,"originationBreakdown":{"byProduct":{"Conventional":{"originated":131,"approximate":false,"hmdaLoanType":1},"FHA":{"originated":0,"approximate":false,"hmdaLoanType":2},"VA":{"originated":0,"approximate":false,"hmdaLoanType":3},"USDA":{"originated":0,"approximate":false,"hmdaLoanType":4}},"totalOriginatedUnits":131,"mergedInsightsFromYear":2024},"declinations":{"available":true,"mergedFromReportingYear":2024,"totalApplications":136,"deniedApplications":1,"withdrawnApplications":4,"incompleteApplications":0,"approvedNotAccepted":0,"purchasedLoans":0,"denialReasons":{"1":0,"2":0,"3":0,"4":0,"5":0,"6":0,"7":0,"8":0,"9":0,"10":0},"denialReasonsSuppressedCount":1},"rank":2548},{"lei":"254900KPCI98XVKU8U39","name":"Acadia Federal Credit Union","nmls":"","type":"Credit Union","dataYear":2024,"orig":131,"dollarVol":15005000,"branches":1,"states":2,"fico":620,"ltv":97,"dti":50,"rate":7.25,"hmdaRate":7.25,"rateSource":"hmda-mlar","products":["Conventional"],"conf":70,"hmdaInsights":{"schemaVersion":2,"reportingYear":2024,"totalApplications":138,"totalOriginated":131,"actionTaken":{"1":131,"2":0,"3":1,"4":4,"5":2,"6":0,"7":0,"8":0},"denialReasons":{"1":0,"2":0,"3":0,"4":0,"5":0,"6":0,"7":0,"8":0,"9":0,"10":0},"denialReasonsSuppressedCount":1,"denialCount":1,"withdrawalCount":4,"incompleteCount":2,"approvedNotAcceptedCount":0,"purchasedLoanCount":0,"originatedMedianInterestRate":7.25,"originatedMedianRateSpread":3.605,"originatedMedianLoanTermMonths":360,"originatedMedianCltv":85,"originatedMedianDti":42.5,"spreadSampleSize":2,"termSampleSize":3,"cltvSampleSize":2,"dtiSampleSize":2,"interestRateSampleSize":4,"loanTypeSummary":{"1":{"applications":138,"originated":131,"dollarVolume":15005000},"2":{"applications":0,"originated":0,"dollarVolume":0},"3":{"applications":0,"originated":0,"dollarVolume":0},"4":{"applications":0,"originated":0,"dollarVolume":0}},"lienOnOriginated":{"1":96,"2":35},"hoepaOnOriginated":{"1":2,"2":112,"3":17},"submissionOnApplications":{"1":8,"1111":130},"initiallyPayableOnApplications":{"1":8,"1111":130},"geographyHhiStates":null,"topStateOriginationShare":null,"stateBreakdown":[],"topCounties":[],"topMsas":[],"quarterlyFromLar":null,"monthlyFromLar":null,"hasActionTakenDate":false,"databrowserSource":false,"source":"modifiedLar-2024-direct","note":"Aggregated directly from FFIEC modified-LAR per-institution file."},"nmlsNumber":null,"legalName":"Acadia Federal Credit Union","dba":null,"originationBreakdown":{"byProduct":{"Conventional":{"originated":131,"approximate":false,"hmdaLoanType":1},"FHA":{"originated":0,"approximate":false,"hmdaLoanType":2},"VA":{"originated":0,"approximate":false,"hmdaLoanType":3},"USDA":{"originated":0,"approximate":false,"hmdaLoanType":4}},"totalOriginatedUnits":131,"mergedInsightsFromYear":2024},"declinations":{"available":true,"mergedFromReportingYear":2024,"totalApplications":138,"deniedApplications":1,"withdrawnApplications":4,"incompleteApplications":2,"approvedNotAccepted":0,"purchasedLoans":0,"denialReasons":{"1":0,"2":0,"3":0,"4":0,"5":0,"6":0,"7":0,"8":0,"9":0,"10":0},"denialReasonsSuppressedCount":1},"rank":2549},{"lei":"54930034MXV88NNFY879","name":"Norwood Co-operative Bank","nmls":"","type":"Bank","dataYear":2024,"orig":131,"dollarVol":94395000,"branches":1,"states":1,"fico":620,"ltv":97,"dti":50,"rate":6.206,"hmdaRate":null,"rateSource":"estimated","products":["Conventional"],"conf":70,"hmdaInsights":{"schemaVersion":2,"reportingYear":2024,"totalApplications":185,"totalOriginated":131,"actionTaken":{"1":131,"2":2,"3":10,"4":15,"5":2,"6":0,"7":12,"8":13},"denialReasons":{"1":0,"2":0,"3":0,"4":0,"5":0,"6":0,"7":0,"8":0,"9":0,"10":0},"denialReasonsSuppressedCount":10,"denialCount":10,"withdrawalCount":15,"incompleteCount":2,"approvedNotAcceptedCount":2,"purchasedLoanCount":0,"originatedMedianInterestRate":null,"originatedMedianRateSpread":null,"originatedMedianLoanTermMonths":null,"originatedMedianCltv":null,"originatedMedianDti":null,"spreadSampleSize":0,"termSampleSize":0,"cltvSampleSize":0,"dtiSampleSize":0,"interestRateSampleSize":0,"loanTypeSummary":{"1":{"applications":185,"originated":131,"dollarVolume":94395000},"2":{"applications":0,"originated":0,"dollarVolume":0},"3":{"applications":0,"originated":0,"dollarVolume":0},"4":{"applications":0,"originated":0,"dollarVolume":0}},"lienOnOriginated":{"1":98,"2":33},"hoepaOnOriginated":{"2":73,"3":58},"submissionOnApplications":{"1111":185},"initiallyPayableOnApplications":{"1111":185},"geographyHhiStates":null,"topStateOriginationShare":null,"stateBreakdown":[],"topCounties":[],"topMsas":[],"quarterlyFromLar":null,"monthlyFromLar":null,"hasActionTakenDate":false,"databrowserSource":false,"source":"modifiedLar-2024-direct","note":"Aggregated directly from FFIEC modified-LAR per-institution file."},"nmlsNumber":null,"legalName":"Norwood Co-operative Bank","dba":null,"originationBreakdown":{"byProduct":{"Conventional":{"originated":131,"approximate":false,"hmdaLoanType":1},"FHA":{"originated":0,"approximate":false,"hmdaLoanType":2},"VA":{"originated":0,"approximate":false,"hmdaLoanType":3},"USDA":{"originated":0,"approximate":false,"hmdaLoanType":4}},"totalOriginatedUnits":131,"mergedInsightsFromYear":2024},"declinations":{"available":true,"mergedFromReportingYear":2024,"totalApplications":185,"deniedApplications":10,"withdrawnApplications":15,"incompleteApplications":2,"approvedNotAccepted":2,"purchasedLoans":0,"denialReasons":{"1":0,"2":0,"3":0,"4":0,"5":0,"6":0,"7":0,"8":0,"9":0,"10":0},"denialReasonsSuppressedCount":10},"rank":2550},{"lei":"54930046JONFO0FON766","name":"Cogent Bank","nmls":"","type":"Bank","dataYear":2024,"orig":131,"dollarVol":65565000,"branches":1,"states":12,"fico":620,"ltv":97,"dti":50,"rate":6.31,"hmdaRate":null,"rateSource":"estimated","products":["Conventional","FHA","VA"],"conf":70,"hmdaInsights":{"schemaVersion":2,"reportingYear":2024,"totalApplications":177,"totalOriginated":131,"actionTaken":{"1":131,"2":9,"3":13,"4":18,"5":6,"6":0,"7":0,"8":0},"denialReasons":{"1":0,"2":0,"3":0,"4":0,"5":0,"6":0,"7":0,"8":0,"9":0,"10":0},"denialReasonsSuppressedCount":13,"denialCount":13,"withdrawalCount":18,"incompleteCount":6,"approvedNotAcceptedCount":9,"purchasedLoanCount":0,"originatedMedianInterestRate":null,"originatedMedianRateSpread":null,"originatedMedianLoanTermMonths":null,"originatedMedianCltv":null,"originatedMedianDti":null,"spreadSampleSize":0,"termSampleSize":0,"cltvSampleSize":0,"dtiSampleSize":0,"interestRateSampleSize":0,"loanTypeSummary":{"1":{"applications":160,"originated":116,"dollarVolume":59970000},"2":{"applications":13,"originated":11,"dollarVolume":3655000},"3":{"applications":4,"originated":4,"dollarVolume":1940000},"4":{"applications":0,"originated":0,"dollarVolume":0}},"lienOnOriginated":{"1":131},"hoepaOnOriginated":{"2":100,"3":31},"submissionOnApplications":{"1111":177},"initiallyPayableOnApplications":{"1111":177},"geographyHhiStates":null,"topStateOriginationShare":null,"stateBreakdown":[],"topCounties":[],"topMsas":[],"quarterlyFromLar":null,"monthlyFromLar":null,"hasActionTakenDate":false,"databrowserSource":false,"source":"modifiedLar-2024-direct","note":"Aggregated directly from FFIEC modified-LAR per-institution file."},"nmlsNumber":null,"legalName":"Cogent Bank","dba":null,"originationBreakdown":{"byProduct":{"Conventional":{"originated":116,"approximate":false,"hmdaLoanType":1},"FHA":{"originated":11,"approximate":false,"hmdaLoanType":2},"VA":{"originated":4,"approximate":false,"hmdaLoanType":3},"USDA":{"originated":0,"approximate":false,"hmdaLoanType":4}},"totalOriginatedUnits":131,"mergedInsightsFromYear":2024},"declinations":{"available":true,"mergedFromReportingYear":2024,"totalApplications":177,"deniedApplications":13,"withdrawnApplications":18,"incompleteApplications":6,"approvedNotAccepted":9,"purchasedLoans":0,"denialReasons":{"1":0,"2":0,"3":0,"4":0,"5":0,"6":0,"7":0,"8":0,"9":0,"10":0},"denialReasonsSuppressedCount":13},"rank":2551},{"lei":"2549007UO49TL9LEDN58","name":"LINKED HOME LOANS, LLC","nmls":"","type":"IMB","dataYear":2024,"orig":131,"dollarVol":62865000,"branches":null,"states":2,"fico":null,"ltv":null,"dti":null,"rate":7.25,"hmdaRate":7.25,"rateSource":"hmda-mlar","products":["Conventional","VA","USDA"],"conf":70,"hmdaInsights":{"schemaVersion":2,"reportingYear":2024,"totalApplications":199,"totalOriginated":131,"actionTaken":{"1":131,"2":18,"3":11,"4":33,"5":0,"6":0,"7":2,"8":4},"denialReasons":{"1":2,"2":4,"3":3,"4":0,"5":0,"6":5,"7":2,"8":0,"9":2,"10":0},"denialReasonsSuppressedCount":0,"denialCount":11,"withdrawalCount":33,"incompleteCount":0,"approvedNotAcceptedCount":18,"purchasedLoanCount":0,"originatedMedianInterestRate":7.25,"originatedMedianRateSpread":0.655,"originatedMedianLoanTermMonths":360,"originatedMedianCltv":80,"originatedMedianDti":44,"spreadSampleSize":123,"termSampleSize":131,"cltvSampleSize":131,"dtiSampleSize":84,"interestRateSampleSize":130,"loanTypeSummary":{"1":{"applications":169,"originated":117,"dollarVolume":58635000},"2":{"applications":1,"originated":0,"dollarVolume":0},"3":{"applications":13,"originated":7,"dollarVolume":3745000},"4":{"applications":16,"originated":7,"dollarVolume":485000}},"lienOnOriginated":{"1":124,"2":7},"hoepaOnOriginated":{"2":119,"3":12},"submissionOnApplications":{"1":199},"initiallyPayableOnApplications":{"1":199},"geographyHhiStates":null,"topStateOriginationShare":null,"stateBreakdown":[],"topCounties":[],"topMsas":[],"quarterlyFromLar":null,"monthlyFromLar":null,"hasActionTakenDate":false,"databrowserSource":false,"source":"modifiedLar-2024-direct","note":"Aggregated directly from FFIEC modified-LAR per-institution file."},"nmlsNumber":null,"legalName":"LINKED HOME LOANS, LLC","dba":null,"originationBreakdown":{"byProduct":{"Conventional":{"originated":117,"approximate":false,"hmdaLoanType":1},"FHA":{"originated":0,"approximate":false,"hmdaLoanType":2},"VA":{"originated":7,"approximate":false,"hmdaLoanType":3},"USDA":{"originated":7,"approximate":false,"hmdaLoanType":4}},"totalOriginatedUnits":131,"mergedInsightsFromYear":2024},"declinations":{"available":true,"mergedFromReportingYear":2024,"totalApplications":199,"deniedApplications":11,"withdrawnApplications":33,"incompleteApplications":0,"approvedNotAccepted":18,"purchasedLoans":0,"denialReasons":{"1":2,"2":4,"3":3,"4":0,"5":0,"6":5,"7":2,"8":0,"9":2,"10":0},"denialReasonsSuppressedCount":0},"rank":2552},{"lei":"549300GV8F4RLYWAB272","name":"MCT CREDIT UNION","nmls":"","type":"Credit Union","dataYear":2024,"orig":131,"dollarVol":17525000,"branches":1,"states":1,"fico":620,"ltv":97,"dti":50,"rate":6.25,"hmdaRate":6.25,"rateSource":"hmda-mlar","products":["Conventional"],"conf":70,"hmdaInsights":{"schemaVersion":2,"reportingYear":2024,"totalApplications":162,"totalOriginated":131,"actionTaken":{"1":131,"2":1,"3":19,"4":11,"5":0,"6":0,"7":0,"8":0},"denialReasons":{"1":5,"2":0,"3":13,"4":1,"5":0,"6":0,"7":0,"8":0,"9":1,"10":0},"denialReasonsSuppressedCount":0,"denialCount":19,"withdrawalCount":11,"incompleteCount":0,"approvedNotAcceptedCount":1,"purchasedLoanCount":0,"originatedMedianInterestRate":6.25,"originatedMedianRateSpread":-0.023,"originatedMedianLoanTermMonths":240,"originatedMedianCltv":73.29,"originatedMedianDti":42,"spreadSampleSize":125,"termSampleSize":131,"cltvSampleSize":131,"dtiSampleSize":47,"interestRateSampleSize":131,"loanTypeSummary":{"1":{"applications":162,"originated":131,"dollarVolume":17525000},"2":{"applications":0,"originated":0,"dollarVolume":0},"3":{"applications":0,"originated":0,"dollarVolume":0},"4":{"applications":0,"originated":0,"dollarVolume":0}},"lienOnOriginated":{"1":97,"2":34},"hoepaOnOriginated":{"2":121,"3":10},"submissionOnApplications":{"1":162},"initiallyPayableOnApplications":{"1":162},"geographyHhiStates":null,"topStateOriginationShare":null,"stateBreakdown":[],"topCounties":[],"topMsas":[],"quarterlyFromLar":null,"monthlyFromLar":null,"hasActionTakenDate":false,"databrowserSource":false,"source":"modifiedLar-2024-direct","note":"Aggregated directly from FFIEC modified-LAR per-institution file."},"nmlsNumber":null,"legalName":"MCT CREDIT UNION","dba":null,"originationBreakdown":{"byProduct":{"Conventional":{"originated":131,"approximate":false,"hmdaLoanType":1},"FHA":{"originated":0,"approximate":false,"hmdaLoanType":2},"VA":{"originated":0,"approximate":false,"hmdaLoanType":3},"USDA":{"originated":0,"approximate":false,"hmdaLoanType":4}},"totalOriginatedUnits":131,"mergedInsightsFromYear":2024},"declinations":{"available":true,"mergedFromReportingYear":2024,"totalApplications":162,"deniedApplications":19,"withdrawnApplications":11,"incompleteApplications":0,"approvedNotAccepted":1,"purchasedLoans":0,"denialReasons":{"1":5,"2":0,"3":13,"4":1,"5":0,"6":0,"7":0,"8":0,"9":1,"10":0},"denialReasonsSuppressedCount":0},"rank":2553},{"lei":"549300I6G5QEIEI78C93","name":"CASE Credit Union","nmls":"","type":"Credit Union","dataYear":2024,"orig":131,"dollarVol":20075000,"branches":1,"states":1,"fico":620,"ltv":97,"dti":50,"rate":7.25,"hmdaRate":7.25,"rateSource":"hmda-mlar","products":["Conventional"],"conf":70,"hmdaInsights":{"schemaVersion":2,"reportingYear":2024,"totalApplications":205,"totalOriginated":131,"actionTaken":{"1":131,"2":0,"3":17,"4":37,"5":7,"6":0,"7":2,"8":11},"denialReasons":{"1":10,"2":0,"3":8,"4":1,"5":0,"6":0,"7":0,"8":0,"9":1,"10":0},"denialReasonsSuppressedCount":0,"denialCount":17,"withdrawalCount":37,"incompleteCount":7,"approvedNotAcceptedCount":0,"purchasedLoanCount":0,"originatedMedianInterestRate":7.25,"originatedMedianRateSpread":0.265,"originatedMedianLoanTermMonths":300,"originatedMedianCltv":75.53,"originatedMedianDti":42,"spreadSampleSize":62,"termSampleSize":131,"cltvSampleSize":124,"dtiSampleSize":46,"interestRateSampleSize":131,"loanTypeSummary":{"1":{"applications":205,"originated":131,"dollarVolume":20075000},"2":{"applications":0,"originated":0,"dollarVolume":0},"3":{"applications":0,"originated":0,"dollarVolume":0},"4":{"applications":0,"originated":0,"dollarVolume":0}},"lienOnOriginated":{"1":125,"2":6},"hoepaOnOriginated":{"2":86,"3":45},"submissionOnApplications":{"1":205},"initiallyPayableOnApplications":{"1":186,"3":19},"geographyHhiStates":null,"topStateOriginationShare":null,"stateBreakdown":[],"topCounties":[],"topMsas":[],"quarterlyFromLar":null,"monthlyFromLar":null,"hasActionTakenDate":false,"databrowserSource":false,"source":"modifiedLar-2024-direct","note":"Aggregated directly from FFIEC modified-LAR per-institution file."},"nmlsNumber":null,"legalName":"CASE Credit Union","dba":null,"originationBreakdown":{"byProduct":{"Conventional":{"originated":131,"approximate":false,"hmdaLoanType":1},"FHA":{"originated":0,"approximate":false,"hmdaLoanType":2},"VA":{"originated":0,"approximate":false,"hmdaLoanType":3},"USDA":{"originated":0,"approximate":false,"hmdaLoanType":4}},"totalOriginatedUnits":131,"mergedInsightsFromYear":2024},"declinations":{"available":true,"mergedFromReportingYear":2024,"totalApplications":205,"deniedApplications":17,"withdrawnApplications":37,"incompleteApplications":7,"approvedNotAccepted":0,"purchasedLoans":0,"denialReasons":{"1":10,"2":0,"3":8,"4":1,"5":0,"6":0,"7":0,"8":0,"9":1,"10":0},"denialReasonsSuppressedCount":0},"rank":2554},{"lei":"54930083VRKEK3SXZJ31","name":"Skowhegan Savings Bank","nmls":"","type":"Bank","dataYear":2024,"orig":131,"dollarVol":34235000,"branches":1,"states":1,"fico":620,"ltv":97,"dti":50,"rate":6.352,"hmdaRate":null,"rateSource":"estimated","products":["Conventional","USDA"],"conf":70,"hmdaInsights":{"schemaVersion":2,"reportingYear":2024,"totalApplications":219,"totalOriginated":131,"actionTaken":{"1":131,"2":3,"3":45,"4":33,"5":7,"6":0,"7":0,"8":0},"denialReasons":{"1":0,"2":0,"3":0,"4":0,"5":0,"6":0,"7":0,"8":0,"9":0,"10":0},"denialReasonsSuppressedCount":45,"denialCount":45,"withdrawalCount":33,"incompleteCount":7,"approvedNotAcceptedCount":3,"purchasedLoanCount":0,"originatedMedianInterestRate":null,"originatedMedianRateSpread":null,"originatedMedianLoanTermMonths":null,"originatedMedianCltv":null,"originatedMedianDti":null,"spreadSampleSize":0,"termSampleSize":0,"cltvSampleSize":0,"dtiSampleSize":0,"interestRateSampleSize":0,"loanTypeSummary":{"1":{"applications":205,"originated":124,"dollarVolume":32910000},"2":{"applications":0,"originated":0,"dollarVolume":0},"3":{"applications":0,"originated":0,"dollarVolume":0},"4":{"applications":14,"originated":7,"dollarVolume":1325000}},"lienOnOriginated":{"1":120,"2":11},"hoepaOnOriginated":{"2":81,"3":50},"submissionOnApplications":{"1111":219},"initiallyPayableOnApplications":{"1111":219},"geographyHhiStates":null,"topStateOriginationShare":null,"stateBreakdown":[],"topCounties":[],"topMsas":[],"quarterlyFromLar":null,"monthlyFromLar":null,"hasActionTakenDate":false,"databrowserSource":false,"source":"modifiedLar-2024-direct","note":"Aggregated directly from FFIEC modified-LAR per-institution file."},"nmlsNumber":null,"legalName":"Skowhegan Savings Bank","dba":null,"originationBreakdown":{"byProduct":{"Conventional":{"originated":124,"approximate":false,"hmdaLoanType":1},"FHA":{"originated":0,"approximate":false,"hmdaLoanType":2},"VA":{"originated":0,"approximate":false,"hmdaLoanType":3},"USDA":{"originated":7,"approximate":false,"hmdaLoanType":4}},"totalOriginatedUnits":131,"mergedInsightsFromYear":2024},"declinations":{"available":true,"mergedFromReportingYear":2024,"totalApplications":219,"deniedApplications":45,"withdrawnApplications":33,"incompleteApplications":7,"approvedNotAccepted":3,"purchasedLoans":0,"denialReasons":{"1":0,"2":0,"3":0,"4":0,"5":0,"6":0,"7":0,"8":0,"9":0,"10":0},"denialReasonsSuppressedCount":45},"rank":2555},{"lei":"25490011JA7PP73YY190","name":"Mt. McKinley Bank","nmls":"","type":"Bank","dataYear":2024,"orig":130,"dollarVol":28440000,"branches":1,"states":1,"fico":620,"ltv":97,"dti":50,"rate":6.246,"hmdaRate":null,"rateSource":"estimated","products":["Conventional","FHA","VA"],"conf":70,"hmdaInsights":{"schemaVersion":2,"reportingYear":2024,"totalApplications":175,"totalOriginated":130,"actionTaken":{"1":130,"2":2,"3":10,"4":32,"5":1,"6":0,"7":0,"8":0},"denialReasons":{"1":0,"2":0,"3":0,"4":0,"5":0,"6":0,"7":0,"8":0,"9":0,"10":0},"denialReasonsSuppressedCount":10,"denialCount":10,"withdrawalCount":32,"incompleteCount":1,"approvedNotAcceptedCount":2,"purchasedLoanCount":0,"originatedMedianInterestRate":null,"originatedMedianRateSpread":null,"originatedMedianLoanTermMonths":null,"originatedMedianCltv":null,"originatedMedianDti":null,"spreadSampleSize":0,"termSampleSize":0,"cltvSampleSize":0,"dtiSampleSize":0,"interestRateSampleSize":0,"loanTypeSummary":{"1":{"applications":148,"originated":110,"dollarVolume":21770000},"2":{"applications":15,"originated":11,"dollarVolume":3875000},"3":{"applications":12,"originated":9,"dollarVolume":2795000},"4":{"applications":0,"originated":0,"dollarVolume":0}},"lienOnOriginated":{"1":113,"2":17},"hoepaOnOriginated":{"2":112,"3":18},"submissionOnApplications":{"1111":175},"initiallyPayableOnApplications":{"1111":175},"geographyHhiStates":null,"topStateOriginationShare":null,"stateBreakdown":[],"topCounties":[],"topMsas":[],"quarterlyFromLar":null,"monthlyFromLar":null,"hasActionTakenDate":false,"databrowserSource":false,"source":"modifiedLar-2024-direct","note":"Aggregated directly from FFIEC modified-LAR per-institution file."},"nmlsNumber":null,"legalName":"Mt. McKinley Bank","dba":null,"originationBreakdown":{"byProduct":{"Conventional":{"originated":110,"approximate":false,"hmdaLoanType":1},"FHA":{"originated":11,"approximate":false,"hmdaLoanType":2},"VA":{"originated":9,"approximate":false,"hmdaLoanType":3},"USDA":{"originated":0,"approximate":false,"hmdaLoanType":4}},"totalOriginatedUnits":130,"mergedInsightsFromYear":2024},"declinations":{"available":true,"mergedFromReportingYear":2024,"totalApplications":175,"deniedApplications":10,"withdrawnApplications":32,"incompleteApplications":1,"approvedNotAccepted":2,"purchasedLoans":0,"denialReasons":{"1":0,"2":0,"3":0,"4":0,"5":0,"6":0,"7":0,"8":0,"9":0,"10":0},"denialReasonsSuppressedCount":10},"rank":2556},{"lei":"254900NZV7NVKXQW9A64","name":"HOME ACCESS FINANCIAL, LLC","nmls":"","type":"IMB","dataYear":2024,"orig":130,"dollarVol":40690000,"branches":1,"states":6,"fico":620,"ltv":97,"dti":50,"rate":6.75,"hmdaRate":6.75,"rateSource":"hmda-mlar","products":["Conventional","FHA"],"conf":70,"hmdaInsights":{"schemaVersion":2,"reportingYear":2024,"totalApplications":215,"totalOriginated":130,"actionTaken":{"1":130,"2":2,"3":0,"4":78,"5":5,"6":0,"7":0,"8":0},"denialReasons":{"1":0,"2":0,"3":0,"4":0,"5":0,"6":0,"7":0,"8":0,"9":0,"10":0},"denialReasonsSuppressedCount":0,"denialCount":0,"withdrawalCount":78,"incompleteCount":5,"approvedNotAcceptedCount":2,"purchasedLoanCount":0,"originatedMedianInterestRate":6.75,"originatedMedianRateSpread":0.558,"originatedMedianLoanTermMonths":360,"originatedMedianCltv":90,"originatedMedianDti":44,"spreadSampleSize":119,"termSampleSize":130,"cltvSampleSize":130,"dtiSampleSize":85,"interestRateSampleSize":130,"loanTypeSummary":{"1":{"applications":130,"originated":77,"dollarVolume":24055000},"2":{"applications":85,"originated":53,"dollarVolume":16635000},"3":{"applications":0,"originated":0,"dollarVolume":0},"4":{"applications":0,"originated":0,"dollarVolume":0}},"lienOnOriginated":{"1":130},"hoepaOnOriginated":{"2":115,"3":15},"submissionOnApplications":{"1":213,"2":2},"initiallyPayableOnApplications":{"1":10,"2":204,"3":1},"geographyHhiStates":null,"topStateOriginationShare":null,"stateBreakdown":[],"topCounties":[],"topMsas":[],"quarterlyFromLar":null,"monthlyFromLar":null,"hasActionTakenDate":false,"databrowserSource":false,"source":"modifiedLar-2024-direct","note":"Aggregated directly from FFIEC modified-LAR per-institution file."},"nmlsNumber":null,"legalName":"HOME ACCESS FINANCIAL, LLC","dba":null,"originationBreakdown":{"byProduct":{"Conventional":{"originated":77,"approximate":false,"hmdaLoanType":1},"FHA":{"originated":53,"approximate":false,"hmdaLoanType":2},"VA":{"originated":0,"approximate":false,"hmdaLoanType":3},"USDA":{"originated":0,"approximate":false,"hmdaLoanType":4}},"totalOriginatedUnits":130,"mergedInsightsFromYear":2024},"declinations":{"available":true,"mergedFromReportingYear":2024,"totalApplications":215,"deniedApplications":0,"withdrawnApplications":78,"incompleteApplications":5,"approvedNotAccepted":2,"purchasedLoans":0,"denialReasons":{"1":0,"2":0,"3":0,"4":0,"5":0,"6":0,"7":0,"8":0,"9":0,"10":0},"denialReasonsSuppressedCount":0},"rank":2557},{"lei":"549300CN9XK83EUACJ34","name":"United Southern Bank","nmls":"","type":"Bank","dataYear":2024,"orig":130,"dollarVol":33960000,"branches":1,"states":1,"fico":620,"ltv":97,"dti":50,"rate":6.279,"hmdaRate":null,"rateSource":"estimated","products":["Conventional"],"conf":70,"hmdaInsights":{"schemaVersion":2,"reportingYear":2024,"totalApplications":173,"totalOriginated":130,"actionTaken":{"1":130,"2":18,"3":12,"4":12,"5":0,"6":0,"7":0,"8":1},"denialReasons":{"1":0,"2":0,"3":0,"4":0,"5":0,"6":0,"7":0,"8":0,"9":0,"10":0},"denialReasonsSuppressedCount":12,"denialCount":12,"withdrawalCount":12,"incompleteCount":0,"approvedNotAcceptedCount":18,"purchasedLoanCount":0,"originatedMedianInterestRate":null,"originatedMedianRateSpread":null,"originatedMedianLoanTermMonths":null,"originatedMedianCltv":null,"originatedMedianDti":null,"spreadSampleSize":0,"termSampleSize":0,"cltvSampleSize":0,"dtiSampleSize":0,"interestRateSampleSize":0,"loanTypeSummary":{"1":{"applications":173,"originated":130,"dollarVolume":33960000},"2":{"applications":0,"originated":0,"dollarVolume":0},"3":{"applications":0,"originated":0,"dollarVolume":0},"4":{"applications":0,"originated":0,"dollarVolume":0}},"lienOnOriginated":{"1":120,"2":10},"hoepaOnOriginated":{"2":85,"3":45},"submissionOnApplications":{"1111":173},"initiallyPayableOnApplications":{"1111":173},"geographyHhiStates":null,"topStateOriginationShare":null,"stateBreakdown":[],"topCounties":[],"topMsas":[],"quarterlyFromLar":null,"monthlyFromLar":null,"hasActionTakenDate":false,"databrowserSource":false,"source":"modifiedLar-2024-direct","note":"Aggregated directly from FFIEC modified-LAR per-institution file."},"nmlsNumber":null,"legalName":"United Southern Bank","dba":null,"originationBreakdown":{"byProduct":{"Conventional":{"originated":130,"approximate":false,"hmdaLoanType":1},"FHA":{"originated":0,"approximate":false,"hmdaLoanType":2},"VA":{"originated":0,"approximate":false,"hmdaLoanType":3},"USDA":{"originated":0,"approximate":false,"hmdaLoanType":4}},"totalOriginatedUnits":130,"mergedInsightsFromYear":2024},"declinations":{"available":true,"mergedFromReportingYear":2024,"totalApplications":173,"deniedApplications":12,"withdrawnApplications":12,"incompleteApplications":0,"approvedNotAccepted":18,"purchasedLoans":0,"denialReasons":{"1":0,"2":0,"3":0,"4":0,"5":0,"6":0,"7":0,"8":0,"9":0,"10":0},"denialReasonsSuppressedCount":12},"rank":2558},{"lei":"5493003T62KDXQ6J4W58","name":"SOUTHEASTERN CREDIT UNION","nmls":"","type":"Credit Union","dataYear":2024,"orig":130,"dollarVol":18950000,"branches":1,"states":2,"fico":620,"ltv":97,"dti":50,"rate":8.45,"hmdaRate":8.45,"rateSource":"hmda-mlar","products":["Conventional"],"conf":70,"hmdaInsights":{"schemaVersion":2,"reportingYear":2024,"totalApplications":147,"totalOriginated":130,"actionTaken":{"1":130,"2":0,"3":5,"4":11,"5":0,"6":0,"7":1,"8":0},"denialReasons":{"1":3,"2":1,"3":1,"4":0,"5":0,"6":0,"7":0,"8":0,"9":1,"10":0},"denialReasonsSuppressedCount":0,"denialCount":5,"withdrawalCount":11,"incompleteCount":0,"approvedNotAcceptedCount":0,"purchasedLoanCount":0,"originatedMedianInterestRate":8.45,"originatedMedianRateSpread":2.33,"originatedMedianLoanTermMonths":180,"originatedMedianCltv":59,"originatedMedianDti":41,"spreadSampleSize":61,"termSampleSize":130,"cltvSampleSize":126,"dtiSampleSize":21,"interestRateSampleSize":129,"loanTypeSummary":{"1":{"applications":147,"originated":130,"dollarVolume":18950000},"2":{"applications":0,"originated":0,"dollarVolume":0},"3":{"applications":0,"originated":0,"dollarVolume":0},"4":{"applications":0,"originated":0,"dollarVolume":0}},"lienOnOriginated":{"1":94,"2":36},"hoepaOnOriginated":{"2":118,"3":12},"submissionOnApplications":{"1":146,"2":1},"initiallyPayableOnApplications":{"1":129,"2":3,"3":15},"geographyHhiStates":null,"topStateOriginationShare":null,"stateBreakdown":[],"topCounties":[],"topMsas":[],"quarterlyFromLar":null,"monthlyFromLar":null,"hasActionTakenDate":false,"databrowserSource":false,"source":"modifiedLar-2024-direct","note":"Aggregated directly from FFIEC modified-LAR per-institution file."},"nmlsNumber":null,"legalName":"SOUTHEASTERN CREDIT UNION","dba":null,"originationBreakdown":{"byProduct":{"Conventional":{"originated":130,"approximate":false,"hmdaLoanType":1},"FHA":{"originated":0,"approximate":false,"hmdaLoanType":2},"VA":{"originated":0,"approximate":false,"hmdaLoanType":3},"USDA":{"originated":0,"approximate":false,"hmdaLoanType":4}},"totalOriginatedUnits":130,"mergedInsightsFromYear":2024},"declinations":{"available":true,"mergedFromReportingYear":2024,"totalApplications":147,"deniedApplications":5,"withdrawnApplications":11,"incompleteApplications":0,"approvedNotAccepted":0,"purchasedLoans":0,"denialReasons":{"1":3,"2":1,"3":1,"4":0,"5":0,"6":0,"7":0,"8":0,"9":1,"10":0},"denialReasonsSuppressedCount":0},"rank":2559},{"lei":"549300LUMAIOXHIFK142","name":"Cy-Fair Federal Credit Union","nmls":"","type":"Credit Union","dataYear":2024,"orig":130,"dollarVol":12170000,"branches":1,"states":1,"fico":620,"ltv":97,"dti":50,"rate":7.97,"hmdaRate":7.97,"rateSource":"hmda-mlar","products":["Conventional"],"conf":70,"hmdaInsights":{"schemaVersion":2,"reportingYear":2024,"totalApplications":172,"totalOriginated":130,"actionTaken":{"1":130,"2":5,"3":22,"4":15,"5":0,"6":0,"7":0,"8":0},"denialReasons":{"1":11,"2":1,"3":7,"4":4,"5":4,"6":1,"7":0,"8":0,"9":4,"10":0},"denialReasonsSuppressedCount":0,"denialCount":22,"withdrawalCount":15,"incompleteCount":0,"approvedNotAcceptedCount":5,"purchasedLoanCount":0,"originatedMedianInterestRate":7.97,"originatedMedianRateSpread":1.95,"originatedMedianLoanTermMonths":180,"originatedMedianCltv":64.4,"originatedMedianDti":42,"spreadSampleSize":128,"termSampleSize":130,"cltvSampleSize":129,"dtiSampleSize":22,"interestRateSampleSize":130,"loanTypeSummary":{"1":{"applications":172,"originated":130,"dollarVolume":12170000},"2":{"applications":0,"originated":0,"dollarVolume":0},"3":{"applications":0,"originated":0,"dollarVolume":0},"4":{"applications":0,"originated":0,"dollarVolume":0}},"lienOnOriginated":{"1":33,"2":97},"hoepaOnOriginated":{"1":2,"2":123,"3":5},"submissionOnApplications":{"1":172},"initiallyPayableOnApplications":{"1":171,"2":1},"geographyHhiStates":null,"topStateOriginationShare":null,"stateBreakdown":[],"topCounties":[],"topMsas":[],"quarterlyFromLar":null,"monthlyFromLar":null,"hasActionTakenDate":false,"databrowserSource":false,"source":"modifiedLar-2024-direct","note":"Aggregated directly from FFIEC modified-LAR per-institution file."},"nmlsNumber":null,"legalName":"Cy-Fair Federal Credit Union","dba":null,"originationBreakdown":{"byProduct":{"Conventional":{"originated":130,"approximate":false,"hmdaLoanType":1},"FHA":{"originated":0,"approximate":false,"hmdaLoanType":2},"VA":{"originated":0,"approximate":false,"hmdaLoanType":3},"USDA":{"originated":0,"approximate":false,"hmdaLoanType":4}},"totalOriginatedUnits":130,"mergedInsightsFromYear":2024},"declinations":{"available":true,"mergedFromReportingYear":2024,"totalApplications":172,"deniedApplications":22,"withdrawnApplications":15,"incompleteApplications":0,"approvedNotAccepted":5,"purchasedLoans":0,"denialReasons":{"1":11,"2":1,"3":7,"4":4,"5":4,"6":1,"7":0,"8":0,"9":4,"10":0},"denialReasonsSuppressedCount":0},"rank":2560}]}